generaltool/__init__.py
generaltool/enforce_literal.py
generaltool/test/test_generaltool.py
generaltool/test/test_literal.py
generaltool-0.1.3.dist-info/LICENSE
generaltool-0.1.3.dist-info/METADATA
generaltool-0.1.3.dist-info/WHEEL
generaltool-0.1.3.dist-info/top_level.txt
generaltool-0.1.3.dist-info/RECORD
